tf_osqp/__init__.py
tf_osqp/tf_osqp.py
tf_osqp-0.1.0.dist-info/LICENSE.txt
tf_osqp-0.1.0.dist-info/METADATA
tf_osqp-0.1.0.dist-info/WHEEL
tf_osqp-0.1.0.dist-info/top_level.txt
tf_osqp-0.1.0.dist-info/RECORD
