Metadata-Version: 2.1
Name: tf-osqp
Version: 0.1.0
Summary: Tensorflow implementation of OSQP solver (unofficial)
Home-page: https://github.com/rishabhjha33/tf-osqp
Author: Rishabh Jha
Author-email: rishabhjha.code@gmail.com
Maintainer: Rishabh Jha
Maintainer-email: rishabhjha.code@gmail.com
License: Apache 2.0
Platform: UNKNOWN
Classifier: Programming Language :: Python :: 3
Classifier: Programming Language :: Python :: 3 :: Only
Classifier: Programming Language :: Python :: 3.5
Classifier: Programming Language :: Python :: 3.6
Classifier: Programming Language :: Python :: 3.7
Classifier: Programming Language :: Python :: 3.8
Classifier: Development Status :: 3 - Alpha
Classifier: License :: OSI Approved :: Apache Software License
Classifier: Operating System :: OS Independent
Classifier: Intended Audience :: Science/Research
Classifier: Natural Language :: English
Requires-Python: >=3.5
Requires-Dist: numpy (>=1.18)
Requires-Dist: tensorflow (>=2.4rc3)
